iservscrapping/__init__.py
iservscrapping/base.py
iservscrapping/errors.py
iservscrapping/fake.py
iservscrapping/task.py
iservscrapping/untis_scrapper.py
iservscrapping-6.0.2.dist-info/LICENSE
iservscrapping-6.0.2.dist-info/WHEEL
iservscrapping-6.0.2.dist-info/METADATA
iservscrapping-6.0.2.dist-info/RECORD
