Metadata-Version: 2.1
Name: iservscrapping
Version: 6.0.2
Summary: This Scrapper can get data from iserv servers hosting Untis plans. (Common in germany)
License: MIT
Author: niwla23
Author-email: alwin@cloudserver.click
Requires-Python: >=3.7,<4.0
Classifier: License :: OSI Approved :: MIT License
Classifier: Programming Language :: Python :: 3
Classifier: Programming Language :: Python :: 3.10
Classifier: Programming Language :: Python :: 3.7
Classifier: Programming Language :: Python :: 3.8
Classifier: Programming Language :: Python :: 3.9
Requires-Dist: Markdown (>=3.3.6,<4.0.0)
Requires-Dist: beautifulsoup4 (>=4.10.0,<5.0.0)
Requires-Dist: lxml (>=4.7.1,<5.0.0)
Requires-Dist: markdownify (>=0.10.2,<0.11.0)
Requires-Dist: requests (>=2.27.1,<3.0.0)
Requires-Dist: requests-cache (>=0.9.1,<0.10.0)
